AUTHORS.rst
CONTRIBUTING.rst
HISTORY.rst
LICENSE
MANIFEST.in
README.rst
setup.cfg
setup.py
wheelmaker
docs/Makefile
docs/authors.rst
docs/conf.py
docs/contributing.rst
docs/history.rst
docs/index.rst
docs/installation.rst
docs/make.bat
docs/readme.rst
docs/usage.rst
tests/__init__.py
tests/test_wheelmaker.py
wheelmaker/__init__.py
wheelmaker/wheelmaker
wheelmaker.egg-info/PKG-INFO
wheelmaker.egg-info/SOURCES.txt
wheelmaker.egg-info/dependency_links.txt
wheelmaker.egg-info/not-zip-safe
wheelmaker.egg-info/requires.txt
wheelmaker.egg-info/top_level.txt