Metadata-Version: 1.1
Name: wheelmaker
Version: 0.1.0
Summary: Creates wheel files from a requirements file
Home-page: https://github.com/fmariluis/wheelmaker
Author: Franco Mariluis
Author-email: fmariluis@msa.com.ar
License: BSD
Keywords: wheelmaker
Platform: UNKNOWN
Classifier: Development Status :: 2 - Pre-Alpha
Classifier: Intended Audience :: Developers
Classifier: License :: OSI Approved :: BSD License
Classifier: Natural Language :: English
Classifier: Programming Language :: Python :: 2
Classifier: Programming Language :: Python :: 2.6
Classifier: Programming Language :: Python :: 2.7
Classifier: Programming Language :: Python :: 3
Classifier: Programming Language :: Python :: 3.3
Classifier: Programming Language :: Python :: 3.4
